pysndlib/clm.c
pysndlib/analog_filter.pyx
pysndlib/dsp.c
pysndlib/dsp.cpython-312-darwin.so
pysndlib/generators.pyx
pysndlib/sndlib.pyx
pysndlib/generators.c
pysndlib/sndlib.h
pysndlib/env.cpython-312-darwin.so
pysndlib/__init__.py
pysndlib/clm.pyx
pysndlib/cclm.pxd
pysndlib/env.pyx
pysndlib/dsp.pxd
pysndlib/dsp.pyx
pysndlib/env.c
pysndlib/clm.pxd
pysndlib/clm.h
pysndlib/generators.cpython-312-darwin.so
pysndlib/csndlib.pxd
pysndlib/cmath_sf.pxd
pysndlib/sndlib.pxd
pysndlib/sndlib.c
pysndlib/generators.pxd
pysndlib/clm_ins.pyx
pysndlib/sndlib.cpython-312-darwin.so
pysndlib/clm.cpython-312-darwin.so
pysndlib/instruments/birds.py
pysndlib/instruments/__init__.cpython-312-darwin.so
pysndlib/instruments/touch_tone.c
pysndlib/instruments/stereo_flute.py
pysndlib/instruments/lbj_piano.cpython-312-darwin.so
pysndlib/instruments/clm_expsrc.py
pysndlib/instruments/pqw.cpython-312-darwin.so
pysndlib/instruments/pianoy.py
pysndlib/instruments/gran_synth.cpython-312-darwin.so
pysndlib/instruments/zn.cpython-312-darwin.so
pysndlib/instruments/pianoy.c
pysndlib/instruments/glassy.c
pysndlib/instruments/stringy.c
pysndlib/instruments/fm_bell.py
pysndlib/instruments/jc_reverb.c
pysndlib/instruments/pluck.cpython-312-darwin.so
pysndlib/instruments/fm_drum.py
pysndlib/instruments/attract.cpython-312-darwin.so
pysndlib/instruments/organish.cpython-312-darwin.so
pysndlib/instruments/spectra.cpython-312-darwin.so
pysndlib/instruments/wurley.py
pysndlib/instruments/za.py
pysndlib/instruments/exp_snd.cpython-312-darwin.so
pysndlib/instruments/exp_snd.py
pysndlib/instruments/fm_trumpet.c
pysndlib/instruments/fm_trumpet.py
pysndlib/instruments/rhodey.c
pysndlib/instruments/nrev.py
pysndlib/instruments/fm_drum.c
pysndlib/instruments/two_tab.c
pysndlib/instruments/glassy.cpython-312-darwin.so
pysndlib/instruments/fm_violin.cpython-312-darwin.so
pysndlib/instruments/machine1.c
pysndlib/instruments/organish.py
pysndlib-0.7.0.dist-info/LICENSE.md
pysndlib-0.7.0.dist-info/RECORD
pysndlib-0.7.0.dist-info/WHEEL
pysndlib-0.7.0.dist-info/top_level.txt
pysndlib-0.7.0.dist-info/METADATA
