Metadata-Version: 2.1
Name: pysndlib
Version: 0.7.0
Summary: A python wrapper around sndlib
Author-email: Todd Ingalls <testcase@asu.edu>
Project-URL: Homepage, https://github.com/testcase/pysndlib
Project-URL: Bug Tracker, https://github.com/testcase/pysndlib/issues
Classifier: Programming Language :: Python :: 3
Classifier: License :: OSI Approved :: MIT License
Classifier: Operating System :: OS Independent
Requires-Python: >=3.10
License-File: LICENSE.md
Requires-Dist: numpy
Requires-Dist: Cython>=3.0.5
